phase_slip/__init__.py
phase_slip/sampler.py
phase_slip_sampler-1.0.0.dist-info/licenses/LICENSE
phase_slip_sampler-1.0.0.dist-info/METADATA
phase_slip_sampler-1.0.0.dist-info/WHEEL
phase_slip_sampler-1.0.0.dist-info/top_level.txt
phase_slip_sampler-1.0.0.dist-info/RECORD
