Metadata-Version: 2.4
Name: phase-slip-sampler
Version: 1.0.0
Summary: An entropic perturbation sampler for LLMs using orthonormal vector rotation and logit anchoring.
Author-email: Michael Christian Morgan <mmorgankorea@gmail.com>
License: MIT License
Project-URL: Homepage, https://github.com/Mmorgan-ML/Phase-Slip-Sampler
Project-URL: Repository, https://github.com/Mmorgan-ML/Phase-Slip-Sampler
Classifier: Programming Language :: Python :: 3
Classifier: License :: OSI Approved :: MIT License
Classifier: Operating System :: OS Independent
Classifier: Topic :: Scientific/Engineering :: Artificial Intelligence
Requires-Python: >=3.8
License-File: LICENSE
Requires-Dist: torch>=1.10.0
Requires-Dist: transformers>=4.0.0
Requires-Dist: numpy
Dynamic: license-file
